Metadata-Version: 1.1
Name: STI-info-scrape
Version: 0.1.0
Summary: Python module to scrape main STI data from SGX main page.
Home-page: https://github.com/spidezad/STI_info_scrape
Author: Tan Kok Hua
Author-email: kokhua81@gmail.com
License: BSD
Download-URL: https://github.com/spidezad/STI_info_scrape/tarball/0.1.0
Platform: UNKNOWN
Classifier: Development Status :: 3 - Alpha
Classifier: Intended Audience :: Developers
Classifier: Programming Language :: Python :: 3
